CHANGELOG
CONTRIBUTING.md
MANIFEST.in
README.md
setup.cfg
setup.py
docs/HISTORY.rst
incolumepy/__init__.py
incolumepy.clinica.egg-info/PKG-INFO
incolumepy.clinica.egg-info/SOURCES.txt
incolumepy.clinica.egg-info/dependency_links.txt
incolumepy.clinica.egg-info/entry_points.txt
incolumepy.clinica.egg-info/namespace_packages.txt
incolumepy.clinica.egg-info/not-zip-safe
incolumepy.clinica.egg-info/requires.txt
incolumepy.clinica.egg-info/top_level.txt
incolumepy/clinica/__init__.py
incolumepy/clinica/credenciais/incolumepy-clinica-95c7132c5028.json