Metadata-Version: 1.1
Name: incolumepy.clinica
Version: 2018.12.1
Summary: pacote incolumepy.clinica
Home-page: http://www.incolume.com.br
Author: @britodfbr
Author-email: contato@incolume.com.br
License: BSD
Project-URL: Documentation, https://gitlab.com/development-incolume/incolumepy.clinica/wikis/home
Project-URL: Funding, None
Project-URL: Say Thanks!, None
Project-URL: Source, https://gitlab.com/development-incolume/incolumepy.clinica
Project-URL: Git prod, https://gitlab.com/development-incolume/incolumepy.clinica.git
Project-URL: Git dev, https://gitlab.com/clinicaesteticabrito/incolumepy.clinica.git
Project-URL: Tracker, https://gitlab.com/clinicaesteticabrito/incolumepy.clinica/issues
Project-URL: Oficial, https://pypi.org/project/incolumepy.clinica/
Keywords: python incolumepy
Platform: UNKNOWN
Classifier: Development Status :: 2 - Pre-Alpha
Classifier: Operating System :: OS Independent
Classifier: Natural Language :: Portuguese (Brazilian)
Classifier: Programming Language :: Python
Classifier: Topic :: Software Development :: Libraries :: Python Modules
Classifier: Topic :: Utilities
